dircleaner/__init__.py
dircleaner/__main__.py
dircleaner/cli.py
dircleaner/func.py
dircleaner-0.1.0.dist-info/METADATA
dircleaner-0.1.0.dist-info/WHEEL
dircleaner-0.1.0.dist-info/entry_points.txt
dircleaner-0.1.0.dist-info/licenses/LICENSE
dircleaner-0.1.0.dist-info/RECORD
