Metadata-Version: 2.1
Name: dircleaner
Version: 0.1.0
Summary: CLI utility to sort directories based on file extensions
Project-URL: Homepage, https://github.com/griquelme/dircleaner
Author: Gabriel Riquelme
License: BSD 3-Clause License
License-File: LICENSE
Classifier: Programming Language :: Python :: 3.9
Classifier: Programming Language :: Python :: 3.10
Requires-Python: >=3.9
Requires-Dist: click>8.1
